tracegraph/__init__.py
tracegraph/graph.py
tracegraph/tracer.py
tracegraph-0.1.0.dist-info/licenses/LICENSE
tracegraph-0.1.0.dist-info/METADATA
tracegraph-0.1.0.dist-info/WHEEL
tracegraph-0.1.0.dist-info/entry_points.txt
tracegraph-0.1.0.dist-info/top_level.txt
tracegraph-0.1.0.dist-info/RECORD
